LICENSE
bigtableql/__init__.py
bigtableql/client.py
bigtableql/insert/__init__.py
bigtableql/insert/composer.py
bigtableql/insert/parser.py
bigtableql/insert/validator.py
bigtableql/insert/writer.py
bigtableql/select/__init__.py
bigtableql/select/composer.py
bigtableql/select/executor.py
bigtableql/select/parser.py
bigtableql/select/scanner.py
bigtableql/select/validator.py
bigtableql-0.1.9.dist-info/LICENSE
bigtableql-0.1.9.dist-info/WHEEL
bigtableql-0.1.9.dist-info/METADATA
bigtableql-0.1.9.dist-info/RECORD
