Metadata-Version: 2.1
Name: bigtableql
Version: 0.1.9
Summary: Query Layer for Google Cloud Bigtable
Home-page: https://github.com/jychen7/BigtableQL
License: MIT
Keywords: arrow,bigtable,datafusion,sql
Author: jychen7
Author-email: jychen7@users.noreply.github.com
Requires-Python: >=3.7,<3.10
Classifier: License :: OSI Approved :: MIT License
Classifier: Programming Language :: Python :: 3
Classifier: Programming Language :: Python :: 3.7
Classifier: Programming Language :: Python :: 3.8
Classifier: Programming Language :: Python :: 3.9
Classifier: Topic :: Software Development :: Build Tools
Classifier: Topic :: Software Development :: Libraries :: Python Modules
Requires-Dist: datafusion (==0.4.0)
Requires-Dist: google-cloud-bigtable (==2.4.0)
Requires-Dist: numpy (==1.21.5)
Requires-Dist: pyarrow (==6.0.1)
Requires-Dist: sqloxide (==0.1.13)
Project-URL: Repository, https://github.com/jychen7/BigtableQL
